corebodytemp/__init__.py
corebodytemp/corebodytemp.py
corebodytemp/datatypes.py
corebodytemp-0.1.1.post2.dist-info/LICENSE.txt
corebodytemp-0.1.1.post2.dist-info/WHEEL
corebodytemp-0.1.1.post2.dist-info/METADATA
corebodytemp-0.1.1.post2.dist-info/RECORD
