Metadata-Version: 2.1
Name: corebodytemp
Version: 0.1.1.post2
Summary: Python BLE API for interacting with CoreBodyTemp Sensors
Home-page: https://github.com/purpl3F0x/corebodytemp
License: MIT
Keywords: corebodytemp,health thermometer,body temperature,ant
Author: Stavros Avramidis
Author-email: stavros9899@gmail.com
Requires-Python: >=3.7,<4.0
Classifier: Development Status :: 1 - Planning
Classifier: Framework :: AsyncIO
Classifier: Intended Audience :: Healthcare Industry
Classifier: License :: OSI Approved :: MIT License
Classifier: Operating System :: Android
Classifier: Operating System :: MacOS :: MacOS X
Classifier: Operating System :: Microsoft :: Windows
Classifier: Operating System :: POSIX :: Linux
Classifier: Programming Language :: Python
Classifier: Programming Language :: Python :: 3
Classifier: Programming Language :: Python :: 3.10
Classifier: Programming Language :: Python :: 3.7
Classifier: Programming Language :: Python :: 3.8
Classifier: Programming Language :: Python :: 3.9
Classifier: Topic :: Scientific/Engineering :: Medical Science Apps.
Classifier: Topic :: Software Development :: Libraries
Requires-Dist: bleak (>=0.14.0,<0.15.0)
Project-URL: Repository, https://github.com/purpl3F0x/corebodytemp
